nanowbind/__init__.py
nanowbind/__main__.py
nanowbind/cmake/darwin-ld-cpython.sym
nanowbind/cmake/darwin-ld-pypy.sym
nanowbind/cmake/nanobind-config-version.cmake
nanowbind/cmake/nanobind-config.cmake
nanowbind/ext/robin_map/include/tsl/robin_growth_policy.h
nanowbind/ext/robin_map/include/tsl/robin_hash.h
nanowbind/ext/robin_map/include/tsl/robin_map.h
nanowbind/include/nanobind/eigen/dense.h
nanowbind/include/nanobind/eigen/sparse.h
nanowbind/include/nanobind/eval.h
nanowbind/include/nanobind/intrusive/counter.h
nanowbind/include/nanobind/intrusive/counter.inl
nanowbind/include/nanobind/intrusive/ref.h
nanowbind/include/nanobind/make_iterator.h
nanowbind/include/nanobind/nanobind.h
nanowbind/include/nanobind/nb_accessor.h
nanowbind/include/nanobind/nb_attr.h
nanowbind/include/nanobind/nb_call.h
nanowbind/include/nanobind/nb_cast.h
nanowbind/include/nanobind/nb_class.h
nanowbind/include/nanobind/nb_defs.h
nanowbind/include/nanobind/nb_descr.h
nanowbind/include/nanobind/nb_enums.h
nanowbind/include/nanobind/nb_error.h
nanowbind/include/nanobind/nb_func.h
nanowbind/include/nanobind/nb_lib.h
nanowbind/include/nanobind/nb_misc.h
nanowbind/include/nanobind/nb_python.h
nanowbind/include/nanobind/nb_traits.h
nanowbind/include/nanobind/nb_tuple.h
nanowbind/include/nanobind/nb_types.h
nanowbind/include/nanobind/ndarray.h
nanowbind/include/nanobind/operators.h
nanowbind/include/nanobind/stl/array.h
nanowbind/include/nanobind/stl/bind_map.h
nanowbind/include/nanobind/stl/bind_vector.h
nanowbind/include/nanobind/stl/chrono.h
nanowbind/include/nanobind/stl/complex.h
nanowbind/include/nanobind/stl/detail/chrono.h
nanowbind/include/nanobind/stl/detail/nb_array.h
nanowbind/include/nanobind/stl/detail/nb_dict.h
nanowbind/include/nanobind/stl/detail/nb_list.h
nanowbind/include/nanobind/stl/detail/nb_set.h
nanowbind/include/nanobind/stl/detail/traits.h
nanowbind/include/nanobind/stl/filesystem.h
nanowbind/include/nanobind/stl/function.h
nanowbind/include/nanobind/stl/list.h
nanowbind-2.1.0.dist-info/METADATA
nanowbind-2.1.0.dist-info/WHEEL
nanowbind-2.1.0.dist-info/licenses/LICENSE
nanowbind-2.1.0.dist-info/RECORD
